summer_modules/__init__.py
summer_modules/ai/__init__.py
summer_modules/ai/deepseek.py
summer_modules/charts/__init__.py
summer_modules/encode/.gitignore
summer_modules/excel/__init__.py
summer_modules/logger/__init__.py
summer_modules/logger/__init__.pyi
summer_modules/markdown/__init__.py
summer_modules/microsoft/__init__.py
summer_modules/microsoft/ms_graph/__init__.py
summer_modules/microsoft/ms_graph/calendar.py
summer_modules/security/__init__.py
summer_modules/security/threat_intelligence/__init__.py
summer_modules/security/threat_intelligence/otx/.gitignore
summer_modules/security/threat_intelligence/otx/__init__.py
summer_modules/security/threat_intelligence/otx/otx_api.py
summer_modules/security/vulnerability/__init__.py
summer_modules/security/vulnerability/attck/.gitignore
summer_modules/security/vulnerability/attck/attck_analyze.py
summer_modules/security/vulnerability/attck/excel_operation.py
summer_modules/security/vulnerability/cnnvd/.gitignore
summer_modules/security/vulnerability/cnnvd/__init__.py
summer_modules/security/vulnerability/cnnvd/info.py
summer_modules/security/vulnerability/cnnvd/查询一个不可能有结果的cveid-Response-1742276655434.http
summer_modules/security/vulnerability/cnvd/index.http
summer_modules/security/vulnerability/cve/.gitignore
summer_modules/security/vulnerability/cve/__init__.py
summer_modules/security/vulnerability/cve/data/cve_info/CVE-2024-44133 /CVE-2024-44133 _cnnvd_search.json
summer_modules/security/vulnerability/cve/data/cve_info/CVE-2024-44133 /CVE-2024-44133 _exploit_db_exp.json
summer_modules/security/vulnerability/cve/data/cve_info/CVE-2024-44133 /CVE-2024-44133 _poc.json
summer_modules/security/vulnerability/cve/info.py
summer_modules/security/vulnerability/cve/poc.py
summer_modules/security/vulnerability/github_repo/.gitignore
summer_modules/security/vulnerability/github_repo/__init__.py
summer_modules/security/vulnerability/github_repo/nuclei.py
summer_modules/security/vulnerability/nvd/.gitignore
summer_modules-0.1.3.dist-info/METADATA
summer_modules-0.1.3.dist-info/WHEEL
summer_modules-0.1.3.dist-info/RECORD
