Metadata-Version: 2.3
Name: summer-modules
Version: 0.1.3
Summary: summery233 python modules
License: MIT
Author: 233
Author-email: ayusummer233@vip.qq.com
Requires-Python: >=3.10
Classifier: License :: OSI Approved :: MIT License
Classifier: Programming Language :: Python :: 3
Classifier: Programming Language :: Python :: 3.10
Classifier: Programming Language :: Python :: 3.11
Classifier: Programming Language :: Python :: 3.12
Classifier: Programming Language :: Python :: 3.13
Requires-Dist: bs4 (>=0.0.2,<0.0.3)
Requires-Dist: cryptography (>=44.0.2,<45.0.0)
Requires-Dist: httpx (>=0.28.1,<0.29.0)
Requires-Dist: matplotlib (>=3.10.3,<4.0.0)
Requires-Dist: openai (>=1.66.3,<2.0.0)
Requires-Dist: openpyxl (>=3.1.5,<4.0.0)
Requires-Dist: toml (>=0.10.2,<0.11.0)
Project-URL: Repository, https://github.com/233Official/summer_modules
